[
  {
    "time": 1716091584000,
    "user": "imbieeel",
    "game": "Steam Key - Random Stuff Ive Given Away"
  },
  {
    "time": 1716091928000,
    "user": "ramone2117",
    "game": "Bravery and Greed"
  },
  {
    "time": 1716092438000,
    "user": "hdsayer",
    "game": "Bayonetta"
  },
  {
    "time": 1716094531000,
    "user": "imbieeel",
    "game": "Loddlenaut"
  },
  {
    "time": 1716096052000,
    "user": "sandeepkumarola",
    "game": "Days Gone"
  },
  {
    "time": 1716098539000,
    "user": "pogboi1985",
    "game": "Planet TD"
  },
  {
    "time": 1716098612000,
    "user": "pogboi1985",
    "game": "Hitsquad Special"
  },
  {
    "time": 1716098967000,
    "user": "belinskaya1998",
    "game": "Mad Max"
  },
  {
    "time": 1716100947000,
    "user": "luiz_hssb",
    "game": "Crashmetal Cyberpunk"
  },
  {
    "time": 1716101021000,
    "user": "lomaster_ua",
    "game": "Doughlings Invasion"
  },
  {
    "time": 1716101658000,
    "user": "ringenburger_",
    "game": "Alien Hostage"
  },
  {
    "time": 1716102194000,
    "user": "adrosa11",
    "game": "Creepy Tale"
  },
  {
    "time": 1716102234000,
    "user": "adrosa11",
    "game": "Symmetry"
  },
  {
    "time": 1716102552000,
    "user": "vondell_play",
    "game": "Creepy Tale"
  },
  {
    "time": 1716102592000,
    "user": "osmaniactr",
    "game": "Hitsquad Special"
  },
  {
    "time": 1716102699000,
    "user": "osmaniactr",
    "game": "Narborion Saga"
  },
  {
    "time": 1716102856000,
    "user": "levone1_",
    "game": "Steam Key - Random Stuff Ive Given Away"
  },
  {
    "time": 1716102978000,
    "user": "yairyel",
    "game": "Hitsquad Special"
  },
  {
    "time": 1716103232000,
    "user": "osmaniactr",
    "game": "The Rescue of Mermaids"
  },
  {
    "time": 1716103640000,
    "user": "bars161rus__",
    "game": "Draw Slasher"
  },
  {
    "time": 1716103794000,
    "user": "divineedareal",
    "game": "Steam Key - Random Stuff Ive Given Away"
  },
  {
    "time": 1716104226000,
    "user": "daveygravy93",
    "game": "Amanda The Adventurer"
  },
  {
    "time": 1716104810000,
    "user": "solosokol",
    "game": "Chernobyl Commando"
  },
  {
    "time": 1716104851000,
    "user": "delidros",
    "game": "Steam Key - Random Stuff Ive Given Away"
  },
  {
    "time": 1716106375000,
    "user": "alfims",
    "game": "Hitsquad Special"
  },
  {
    "time": 1716107279000,
    "user": "andraz201",
    "game": "Bravery and Greed"
  },
  {
    "time": 1716107452000,
    "user": "alexshadowsky",
    "game": "Hitsquad Special"
  },
  {
    "time": 1716107602000,
    "user": "memowho1",
    "game": "Oaken"
  },
  {
    "time": 1716107845000,
    "user": "snorkovsky",
    "game": "Love is Dead"
  },
  {
    "time": 1716107882000,
    "user": "samsikua",
    "game": "Them and Us"
  },
  {
    "time": 1716108247000,
    "user": "8ateeight",
    "game": "Starfringe Adversus"
  },
  {
    "time": 1716108447000,
    "user": "melak1306",
    "game": "Steam Key - Random Stuff Ive Given Away"
  },
  {
    "time": 1716109499000,
    "user": "pegman__",
    "game": "Amanda The Adventurer"
  },
  {
    "time": 1716109568000,
    "user": "pegman__",
    "game": "Loddlenaut"
  },
  {
    "time": 1716109659000,
    "user": "zyzio2202",
    "game": "Heavenly Bodies"
  },
  {
    "time": 1716109949000,
    "user": "boriskazman",
    "game": "Shadow of the Tomb Raider Definitive Edition"
  },
  {
    "time": 1716110564000,
    "user": "beautiful_life_de",
    "game": "Hitsquad Special"
  },
  {
    "time": 1716111284000,
    "user": "sambaskyxd",
    "game": "Steam Key - Random Stuff Ive Given Away"
  },
  {
    "time": 1716112084000,
    "user": "ykhanaha",
    "game": "The Nightmare"
  },
  {
    "time": 1716112770000,
    "user": "mrstasi4ka",
    "game": "Hitsquad Special"
  },
  {
    "time": 1716112891000,
    "user": "venia0000",
    "game": "Narborion Saga"
  },
  {
    "time": 1716113548000,
    "user": "sansay89",
    "game": "Hitsquad Special"
  },
  {
    "time": 1716114007000,
    "user": "johnstefin",
    "game": "Steam Key - Random Stuff Ive Given Away"
  },
  {
    "time": 1716114775000,
    "user": "pata_3",
    "game": "The Anacrusis"
  },
  {
    "time": 1716115611000,
    "user": "drimon33113",
    "game": "Steam Key - Random Stuff Ive Given Away"
  },
  {
    "time": 1716115798000,
    "user": "drimon33113",
    "game": "Hitsquad Special"
  },
  {
    "time": 1716115933000,
    "user": "pata_3",
    "game": "Railroad Tycoon 2 Platinum"
  },
  {
    "time": 1716115952000,
    "user": "airexer",
    "game": "Steam Key - Random Stuff Ive Given Away"
  },
  {
    "time": 1716116271000,
    "user": "prostojulia_",
    "game": "Steam Key - Random Stuff Ive Given Away"
  },
  {
    "time": 1716117050000,
    "user": "melihsaltug23",
    "game": "Turnip Boy Commits Tax Evasion"
  },
  {
    "time": 1716117116000,
    "user": "melihsaltug23",
    "game": "Worms Rumble"
  },
  {
    "time": 1716117268000,
    "user": "zencefillikurabiye35",
    "game": "Bravery and Greed"
  },
  {
    "time": 1716117391000,
    "user": "ahdpe",
    "game": "Amanda The Adventurer"
  },
  {
    "time": 1716117408000,
    "user": "sezerorkun",
    "game": "Fashion Police"
  },
  {
    "time": 1716117459000,
    "user": "naz5945",
    "game": "Steam Key - Random Stuff Ive Given Away"
  },
  {
    "time": 1716117497000,
    "user": "jordanserkan",
    "game": "Downwell"
  },
  {
    "time": 1716117624000,
    "user": "zelasis",
    "game": "Civcity Rome"
  },
  {
    "time": 1716117627000,
    "user": "vitaliy_kamalin",
    "game": "Steam Key - Random Stuff Ive Given Away"
  },
  {
    "time": 1716117665000,
    "user": "vitaliy_kamalin",
    "game": "Hitsquad Special"
  },
  {
    "time": 1716117855000,
    "user": "kvitkx",
    "game": "Children of Silentown"
  },
  {
    "time": 1716117895000,
    "user": "chi1cag0",
    "game": "System Shock Enhanced Edition"
  },
  {
    "time": 1716117915000,
    "user": "kvitkx",
    "game": "Steam Key - Random Stuff Ive Given Away"
  },
  {
    "time": 1716118297000,
    "user": "charos24",
    "game": "Steam Key - Random Stuff Ive Given Away"
  },
  {
    "time": 1716118425000,
    "user": "ducksomething11",
    "game": "Steam Key - Random Stuff Ive Given Away"
  },
  {
    "time": 1716118464000,
    "user": "max0145",
    "game": "Steam Key - Random Stuff Ive Given Away"
  },
  {
    "time": 1716118844000,
    "user": "anolandsfit",
    "game": "The Deed"
  },
  {
    "time": 1716119039000,
    "user": "100bitlive",
    "game": "Fashion Police"
  },
  {
    "time": 1716119149000,
    "user": "couyok2",
    "game": "Hidden and Dangerous Action Pack"
  },
  {
    "time": 1716119387000,
    "user": "infinite_games_yaniek",
    "game": "Steam Key - Random Stuff Ive Given Away"
  },
  {
    "time": 1716119512000,
    "user": "ruzzenko",
    "game": "Chicken Police"
  },
  {
    "time": 1716119787000,
    "user": "infinite_games_yaniek",
    "game": "Armello"
  },
  {
    "time": 1716119986000,
    "user": "infinite_games_yaniek",
    "game": "Pawnbarian"
  },
  {
    "time": 1716120026000,
    "user": "daniempirerevolution",
    "game": "Narborion Saga"
  },
  {
    "time": 1716120142000,
    "user": "infinite_games_yaniek",
    "game": "Afterimage"
  },
  {
    "time": 1716120653000,
    "user": "brigada77777",
    "game": "Wolfenstein The Old Blood"
  },
  {
    "time": 1716120951000,
    "user": "eugene_kuz",
    "game": "Exile To Death"
  },
  {
    "time": 1716121372000,
    "user": "fvbljvfhe28",
    "game": "Blackguards Deluxe Edition"
  },
  {
    "time": 1716121830000,
    "user": "neliunmih",
    "game": "Creepy Tale"
  },
  {
    "time": 1716121989000,
    "user": "bsvsbsvs",
    "game": "Steam Key - Random Stuff Ive Given Away"
  },
  {
    "time": 1716122788000,
    "user": "gnom133114454",
    "game": "Army Men RTS"
  },
  {
    "time": 1716122924000,
    "user": "fakicro",
    "game": "Army Men RTS"
  },
  {
    "time": 1716123265000,
    "user": "iluminaria",
    "game": "Eight Mini Racers"
  },
  {
    "time": 1716123287000,
    "user": "iluminaria",
    "game": "Brother Wings"
  },
  {
    "time": 1716124394000,
    "user": "contract_killerz",
    "game": "Steam Key - Random Stuff Ive Given Away"
  },
  {
    "time": 1716124657000,
    "user": "extremegeo",
    "game": "Steam Key - Random Stuff Ive Given Away"
  },
  {
    "time": 1716124870000,
    "user": "sany1124",
    "game": "Steam Key - Random Stuff Ive Given Away"
  },
  {
    "time": 1716124917000,
    "user": "nyytrohx",
    "game": "A Jugglers Tale"
  },
  {
    "time": 1716124929000,
    "user": "munital1",
    "game": "Hidden and Dangerous Action Pack"
  },
  {
    "time": 1716125261000,
    "user": "shinee062651",
    "game": "Foretales"
  },
  {
    "time": 1716125594000,
    "user": "mark17092000",
    "game": "Foretales"
  },
  {
    "time": 1716125988000,
    "user": "thats_uranum",
    "game": "Turbo Golf Racing"
  },
  {
    "time": 1716126455000,
    "user": "rg_line",
    "game": "Steam Key - Random Stuff Ive Given Away"
  },
  {
    "time": 1716126542000,
    "user": "v001_",
    "game": "Campfire One of Us Is The Killer"
  },
  {
    "time": 1716126583000,
    "user": "rghype",
    "game": "Steam Key - Random Stuff Ive Given Away"
  },
  {
    "time": 1716127111000,
    "user": "jackthewalker",
    "game": "Steam Key - Random Stuff Ive Given Away"
  },
  {
    "time": 1716127140000,
    "user": "cerberus_000001",
    "game": "Revita"
  },
  {
    "time": 1716127242000,
    "user": "dragoniteofepicness",
    "game": "Amanda The Adventurer"
  },
  {
    "time": 1716127513000,
    "user": "knottt_",
    "game": "Steam Key - Random Stuff Ive Given Away"
  },
  {
    "time": 1716128297000,
    "user": "fineaszu",
    "game": "Narborion Saga"
  },
  {
    "time": 1716128314000,
    "user": "jahlambai",
    "game": "Steam Key - Random Stuff Ive Given Away"
  },
  {
    "time": 1716128343000,
    "user": "manga_456",
    "game": "Mind Spheres"
  }
]