[
  {
    "time": 1742098445000,
    "user": "sweetcuppincake",
    "game": "Cavern of Dreams"
  },
  {
    "time": 1742098772000,
    "user": "pogboi1985",
    "game": "EA APP KEY Wild Hearts"
  },
  {
    "time": 1742099298000,
    "user": "anarcopunkrj",
    "game": "Cavern of Dreams"
  },
  {
    "time": 1742099620000,
    "user": "jperez277",
    "game": "Cavern of Dreams"
  },
  {
    "time": 1742100306000,
    "user": "rickydickie",
    "game": "Cavern of Dreams"
  },
  {
    "time": 1742100417000,
    "user": "lycankai",
    "game": "Cavern of Dreams"
  }
]