[
  {
    "time": 1732425559000,
    "user": "rocketzinph",
    "game": "Creepy Tale"
  },
  {
    "time": 1732425595000,
    "user": "rocketzinph",
    "game": "Reignmaker"
  },
  {
    "time": 1732425689000,
    "user": "rocketzinph",
    "game": "Oddworld Abes Oddysee"
  },
  {
    "time": 1732425738000,
    "user": "rocketzinph",
    "game": "Saturday Morning RPG"
  },
  {
    "time": 1732427983000,
    "user": "diupwork",
    "game": "Steam Key - Random Stuff Ive Given Away"
  },
  {
    "time": 1732428109000,
    "user": "higamestv",
    "game": "Bayonetta"
  },
  {
    "time": 1732429130000,
    "user": "beardedeathgaming",
    "game": "Reignmaker"
  },
  {
    "time": 1732429584000,
    "user": "dr35gs",
    "game": "Persona 4 Golden"
  },
  {
    "time": 1732430517000,
    "user": "joowon_c",
    "game": "Forewarned"
  },
  {
    "time": 1732430727000,
    "user": "ares1986god",
    "game": "Pobeda"
  },
  {
    "time": 1732430797000,
    "user": "nytspav",
    "game": "Steam Key - Random Stuff Ive Given Away"
  },
  {
    "time": 1732430813000,
    "user": "ares1986god",
    "game": "Wayout 2"
  },
  {
    "time": 1732431074000,
    "user": "ares1986god",
    "game": "Orbital Racer"
  },
  {
    "time": 1732431303000,
    "user": "ares1986god",
    "game": "Creepy Tale"
  },
  {
    "time": 1732431373000,
    "user": "xthissuxxx",
    "game": "The Deed"
  },
  {
    "time": 1732431426000,
    "user": "nytspav",
    "game": "Hitsquad Special #4"
  },
  {
    "time": 1732431475000,
    "user": "nytspav",
    "game": "Caveman World Mountains of Unga Boonga"
  },
  {
    "time": 1732431659000,
    "user": "ares1986god",
    "game": "Jack Move"
  },
  {
    "time": 1732431952000,
    "user": "ares1986god",
    "game": "The Anacrusis"
  },
  {
    "time": 1732432012000,
    "user": "player0451",
    "game": "Steam Key - Random Stuff Ive Given Away"
  },
  {
    "time": 1732432559000,
    "user": "mewingmussel",
    "game": "Behind The Frame The Finest Scenery"
  },
  {
    "time": 1732432787000,
    "user": "hellyeah4er",
    "game": "UFO Afterlight"
  },
  {
    "time": 1732432871000,
    "user": "feiling",
    "game": "Sid Meier's Starships"
  },
  {
    "time": 1732433420000,
    "user": "starofhighhope",
    "game": "Balatro"
  },
  {
    "time": 1732435301000,
    "user": "buckjellybean",
    "game": "Stalker Call of Pripyat"
  },
  {
    "time": 1732435360000,
    "user": "swapnoneel",
    "game": "Jusant"
  },
  {
    "time": 1732436278000,
    "user": "ferdik09",
    "game": "Garden Life A Cozy Simulator"
  },
  {
    "time": 1732436300000,
    "user": "yacomango",
    "game": "Particula"
  },
  {
    "time": 1732436438000,
    "user": "ghostrunner_games",
    "game": "Necroworm"
  },
  {
    "time": 1732437057000,
    "user": "ovosh_1337",
    "game": "Honey I Joined a Cult"
  },
  {
    "time": 1732437101000,
    "user": "thalesulisses",
    "game": "Sid Meier's Starships"
  }
]