[
  {
    "time": 1717301795000,
    "user": "joshuadhoni",
    "game": "Tinykin"
  },
  {
    "time": 1717301872000,
    "user": "hackballer",
    "game": "Wolfenstein Youngblood Deluxe"
  },
  {
    "time": 1717302664000,
    "user": "knighto70",
    "game": "Black Skylands"
  },
  {
    "time": 1717303492000,
    "user": "bifflus",
    "game": "Titeuf Mega Party"
  },
  {
    "time": 1717303735000,
    "user": "boundarykkv",
    "game": "The Walking Dead Season 2"
  },
  {
    "time": 1717304179000,
    "user": "waldin_",
    "game": "Steam Key - Random Stuff Ive Given Away"
  },
  {
    "time": 1717305157000,
    "user": "jeffrey_sexy_dahmer",
    "game": "A Jugglers Tale"
  },
  {
    "time": 1717305837000,
    "user": "bifflus",
    "game": "Achievement Killer"
  },
  {
    "time": 1717305856000,
    "user": "bifflus",
    "game": "Achievement Killer"
  },
  {
    "time": 1717305910000,
    "user": "constantinrs",
    "game": "Exile To Death"
  },
  {
    "time": 1717306111000,
    "user": "bifflus",
    "game": "Level Up Simulator"
  },
  {
    "time": 1717306145000,
    "user": "chiku2006",
    "game": "Steam Key - Random Stuff Ive Given Away"
  },
  {
    "time": 1717307395000,
    "user": "p4t659n",
    "game": "Lego The Lord of the Rings"
  },
  {
    "time": 1717309359000,
    "user": "trev_xd",
    "game": "Civcity Rome"
  },
  {
    "time": 1717309562000,
    "user": "romanovpetrnew",
    "game": "Creaks"
  },
  {
    "time": 1717309746000,
    "user": "yobi5tailedfox",
    "game": "Oddworld Abes Exoddus"
  },
  {
    "time": 1717310069000,
    "user": "chiuhihi",
    "game": "Lords and Villeins"
  },
  {
    "time": 1717310374000,
    "user": "mitchko5",
    "game": "Magnifico"
  },
  {
    "time": 1717310570000,
    "user": "eugene960",
    "game": "Steam Key - Random Stuff Ive Given Away"
  },
  {
    "time": 1717310782000,
    "user": "t0m0h154",
    "game": "Steam Key - Random Stuff Ive Given Away"
  },
  {
    "time": 1717311730000,
    "user": "popagaming",
    "game": "System Shock Enhanced Edition"
  },
  {
    "time": 1717311770000,
    "user": "popagaming",
    "game": "Kingdom Defense"
  },
  {
    "time": 1717311821000,
    "user": "t0m0h154",
    "game": "Pixross"
  },
  {
    "time": 1717311900000,
    "user": "popagaming",
    "game": "Lilas Sky Ark"
  },
  {
    "time": 1717312090000,
    "user": "t0m0h154",
    "game": "Pixross"
  },
  {
    "time": 1717312763000,
    "user": "twichazuvesplay",
    "game": "Steam Key - Random Stuff Ive Given Away"
  },
  {
    "time": 1717312837000,
    "user": "gareppa",
    "game": "Shutshimi"
  },
  {
    "time": 1717313066000,
    "user": "flairbro",
    "game": "Tinykin"
  },
  {
    "time": 1717313463000,
    "user": "tincelki",
    "game": "Tin Can"
  },
  {
    "time": 1717313974000,
    "user": "popagaming",
    "game": "Tin Can"
  },
  {
    "time": 1717315294000,
    "user": "kketan77",
    "game": "The Spiral Scouts"
  },
  {
    "time": 1717315374000,
    "user": "lolgems22",
    "game": "Rebel Inc Escalation"
  },
  {
    "time": 1717315661000,
    "user": "kolug90",
    "game": "Steam Key - Random Stuff Ive Given Away"
  },
  {
    "time": 1717315880000,
    "user": "kazimierz1904",
    "game": "Remothered: Broken Porcelain"
  },
  {
    "time": 1717316649000,
    "user": "hortreex",
    "game": "Potatoman Seeks the Troof"
  },
  {
    "time": 1717316854000,
    "user": "t0m0h154",
    "game": "Pixross"
  },
  {
    "time": 1717318450000,
    "user": "realvelosh",
    "game": "Loddlenaut"
  },
  {
    "time": 1717318482000,
    "user": "realvelosh",
    "game": "SCP Secret Files"
  },
  {
    "time": 1717319896000,
    "user": "dripohollik",
    "game": "Fashion Police"
  },
  {
    "time": 1717319931000,
    "user": "dripohollik",
    "game": "A Jugglers Tale"
  },
  {
    "time": 1717320070000,
    "user": "falcheckor",
    "game": "Rage in Peace"
  },
  {
    "time": 1717320204000,
    "user": "gtbr007",
    "game": "Creepy Tale"
  },
  {
    "time": 1717320412000,
    "user": "rinneyann",
    "game": "Railroad Tycoon 3"
  },
  {
    "time": 1717320438000,
    "user": "gtbr007",
    "game": "Haunted Island Frog Detective Game"
  },
  {
    "time": 1717320492000,
    "user": "gtbr007",
    "game": "Civcity Rome"
  },
  {
    "time": 1717320977000,
    "user": "momomobobo",
    "game": "Ad Infinitum"
  },
  {
    "time": 1717320984000,
    "user": "rinneyann",
    "game": "Symphony of War The Nephilim Saga"
  },
  {
    "time": 1717321041000,
    "user": "xyberbonk",
    "game": "Rage in Peace"
  },
  {
    "time": 1717321120000,
    "user": "xyberbonk",
    "game": "Excavation of Hobs Barrow"
  },
  {
    "time": 1717321200000,
    "user": "speedw4goon",
    "game": "$5 Steam Code"
  },
  {
    "time": 1717321207000,
    "user": "zydent",
    "game": "$5 Steam Code"
  },
  {
    "time": 1717321246000,
    "user": "andresfy5",
    "game": "$5 Steam Code"
  },
  {
    "time": 1717321393000,
    "user": "yobi5tailedfox",
    "game": "Creepy Tale"
  },
  {
    "time": 1717321501000,
    "user": "yobi5tailedfox",
    "game": "Xel"
  },
  {
    "time": 1717321707000,
    "user": "chanelno69",
    "game": "$5 Steam Code"
  },
  {
    "time": 1717321710000,
    "user": "kaef456",
    "game": "$5 Steam Code"
  },
  {
    "time": 1717321983000,
    "user": "zzzeraora",
    "game": "Mortal Kombat 11"
  },
  {
    "time": 1717322009000,
    "user": "dahhel",
    "game": "Rage in Peace"
  },
  {
    "time": 1717322081000,
    "user": "yassnichou",
    "game": "$5 Steam Code"
  },
  {
    "time": 1717322142000,
    "user": "bissateszouinates",
    "game": "$5 Steam Code"
  },
  {
    "time": 1717322340000,
    "user": "nowhaile",
    "game": "Steam Key - Random Stuff Ive Given Away"
  },
  {
    "time": 1717322459000,
    "user": "nactkz",
    "game": "$5 Steam Code"
  },
  {
    "time": 1717322471000,
    "user": "serezag",
    "game": "$5 Steam Code"
  },
  {
    "time": 1717322741000,
    "user": "blackradler01",
    "game": "$5 Steam Code"
  },
  {
    "time": 1717322918000,
    "user": "vasyakruglov",
    "game": "DOOM"
  },
  {
    "time": 1717322971000,
    "user": "sciencef",
    "game": "Steam Key - Random Stuff Ive Given Away"
  },
  {
    "time": 1717323234000,
    "user": "hvaki_spark",
    "game": "Mind Spheres"
  },
  {
    "time": 1717323341000,
    "user": "mrblackcat13",
    "game": "S.W.I.N.E. HD Remaster"
  },
  {
    "time": 1717323706000,
    "user": "mrblackcat13",
    "game": "Rebel Inc Escalation"
  },
  {
    "time": 1717323716000,
    "user": "zwjjwzz",
    "game": "Foretales"
  },
  {
    "time": 1717323744000,
    "user": "zwjjwzz",
    "game": "Souldiers"
  },
  {
    "time": 1717323758000,
    "user": "zwjjwzz",
    "game": "Hyper Gunsport"
  },
  {
    "time": 1717323920000,
    "user": "i_tez",
    "game": "Steam Key - Random Stuff Ive Given Away"
  },
  {
    "time": 1717324152000,
    "user": "adrosa11",
    "game": "Homeworld Remastered Collection"
  },
  {
    "time": 1717324200000,
    "user": "adrosa11",
    "game": "Homeworld Deserts of Kharak"
  },
  {
    "time": 1717325047000,
    "user": "mathiasmey",
    "game": "Guts and Glory"
  },
  {
    "time": 1717325132000,
    "user": "isl0w",
    "game": "Creepy Tale"
  },
  {
    "time": 1717325293000,
    "user": "adrosa11",
    "game": "System Shock 2"
  },
  {
    "time": 1717325466000,
    "user": "digital_dom_",
    "game": "Steam Key - Random Stuff Ive Given Away"
  },
  {
    "time": 1717325769000,
    "user": "davidkli",
    "game": "Izmir and Independence Simulator"
  },
  {
    "time": 1717326194000,
    "user": "mincak",
    "game": "Steam Key - Random Stuff Ive Given Away"
  },
  {
    "time": 1717326832000,
    "user": "gabriel__2014",
    "game": "Soulblight"
  },
  {
    "time": 1717328631000,
    "user": "artedeivideogiochi",
    "game": "Hover Hazard"
  },
  {
    "time": 1717328715000,
    "user": "artedeivideogiochi",
    "game": "Exile To Death"
  },
  {
    "time": 1717328725000,
    "user": "ponponoon",
    "game": "Steam Key - Random Stuff Ive Given Away"
  },
  {
    "time": 1717328821000,
    "user": "artedeivideogiochi",
    "game": "Blaite"
  },
  {
    "time": 1717328900000,
    "user": "artedeivideogiochi",
    "game": "Achievement Killer"
  },
  {
    "time": 1717328924000,
    "user": "artedeivideogiochi",
    "game": "The Nightmare"
  },
  {
    "time": 1717328940000,
    "user": "artedeivideogiochi",
    "game": "Level Up Simulator"
  },
  {
    "time": 1717328987000,
    "user": "welovechowderchu",
    "game": "Forgotten City"
  },
  {
    "time": 1717329017000,
    "user": "bouchart",
    "game": "Stikir"
  },
  {
    "time": 1717329744000,
    "user": "sezerorkun",
    "game": "Them and Us"
  },
  {
    "time": 1717329747000,
    "user": "slyislands",
    "game": "S.W.I.N.E. HD Remaster"
  },
  {
    "time": 1717329785000,
    "user": "slyislands",
    "game": "Turbo Golf Racing"
  },
  {
    "time": 1717329844000,
    "user": "slyislands",
    "game": "Excavation of Hobs Barrow"
  },
  {
    "time": 1717330041000,
    "user": "melihsaltug23",
    "game": "911 Operator"
  },
  {
    "time": 1717330156000,
    "user": "twitchergamerg0d",
    "game": "Lust For Darkness"
  },
  {
    "time": 1717330240000,
    "user": "orangejuice716",
    "game": "Dreamscaper"
  },
  {
    "time": 1717330251000,
    "user": "nikzor888",
    "game": "Chicken Labyrinth Puzzles"
  },
  {
    "time": 1717330312000,
    "user": "praying4you717",
    "game": "Battlewake"
  },
  {
    "time": 1717330314000,
    "user": "nikzor888",
    "game": "Chicken Labyrinth Puzzles"
  },
  {
    "time": 1717330388000,
    "user": "purplechain728",
    "game": "Batora Lost Haven"
  },
  {
    "time": 1717330444000,
    "user": "challenger885",
    "game": "Chicken Labyrinth Puzzles"
  },
  {
    "time": 1717330471000,
    "user": "challenger885",
    "game": "Chicken Labyrinth Puzzles"
  },
  {
    "time": 1717330550000,
    "user": "thalesulisses",
    "game": "Shutshimi"
  },
  {
    "time": 1717331939000,
    "user": "jajajazdes",
    "game": "XCOM Chimera Squad"
  },
  {
    "time": 1717333788000,
    "user": "af4xg0d",
    "game": "Path of Giants"
  },
  {
    "time": 1717333865000,
    "user": "ainmast911",
    "game": "Monster Crown"
  },
  {
    "time": 1717333985000,
    "user": "tomg777",
    "game": "Steam Key - Random Stuff Ive Given Away"
  },
  {
    "time": 1717334092000,
    "user": "askanzone",
    "game": "Haunted Island Frog Detective Game"
  },
  {
    "time": 1717334188000,
    "user": "aurolox077",
    "game": "Saturday Morning RPG"
  },
  {
    "time": 1717334305000,
    "user": "pontdan7",
    "game": "Post Void"
  },
  {
    "time": 1717334613000,
    "user": "kingivingi",
    "game": "Steam Key - Random Stuff Ive Given Away"
  },
  {
    "time": 1717334675000,
    "user": "htpglass",
    "game": "Omno"
  },
  {
    "time": 1717334816000,
    "user": "jlinsertz",
    "game": "Hotshot Racing"
  },
  {
    "time": 1717334828000,
    "user": "wa1jloff",
    "game": "Rage in Peace"
  },
  {
    "time": 1717334875000,
    "user": "florenjy",
    "game": "Ogre"
  },
  {
    "time": 1717335184000,
    "user": "xz3nxz4n",
    "game": "Loddlenaut"
  },
  {
    "time": 1717335488000,
    "user": "switchn375",
    "game": "Rage in Peace"
  },
  {
    "time": 1717335623000,
    "user": "mxhunn",
    "game": "The Walking Dead New Frontier"
  },
  {
    "time": 1717335988000,
    "user": "shinee062651",
    "game": "Path of Giants"
  },
  {
    "time": 1717336327000,
    "user": "forsteamgames",
    "game": "Steam Key - Random Stuff Ive Given Away"
  },
  {
    "time": 1717337762000,
    "user": "artedeivideogiochi",
    "game": "Steam Key - Random Stuff Ive Given Away"
  },
  {
    "time": 1717337954000,
    "user": "blamerx_",
    "game": "Holy Potatoes Were In Space"
  },
  {
    "time": 1717338302000,
    "user": "alburldador",
    "game": "Downwell"
  },
  {
    "time": 1717338499000,
    "user": "kingdoom_619",
    "game": "Children of Silentown"
  },
  {
    "time": 1717338536000,
    "user": "wiseshadow1990",
    "game": "Creepy Tale"
  },
  {
    "time": 1717339698000,
    "user": "maksimust",
    "game": "Railroad Tycoon 3"
  },
  {
    "time": 1717340180000,
    "user": "samuelbr1z",
    "game": "Guns and Fishes"
  },
  {
    "time": 1717340226000,
    "user": "alkeaz",
    "game": "Worms Rumble"
  },
  {
    "time": 1717341166000,
    "user": "xulaster",
    "game": "Achievement Killer"
  },
  {
    "time": 1717341188000,
    "user": "xulaster",
    "game": "Level Up Simulator"
  },
  {
    "time": 1717341589000,
    "user": "hvaki_spark",
    "game": "The Deed"
  },
  {
    "time": 1717341760000,
    "user": "mira5699",
    "game": "Lego The Lord of the Rings"
  },
  {
    "time": 1717342041000,
    "user": "hvaki_spark",
    "game": "Magnifico"
  },
  {
    "time": 1717342202000,
    "user": "hvaki_spark",
    "game": "Gold Rush Classic"
  },
  {
    "time": 1717342542000,
    "user": "boostlethal",
    "game": "Trover Saves The Universe"
  },
  {
    "time": 1717343065000,
    "user": "607i",
    "game": "Creepy Tale"
  },
  {
    "time": 1717344086000,
    "user": "iriyasu_m",
    "game": "Sid Meiers Colonization"
  },
  {
    "time": 1717344161000,
    "user": "nevropatolog92",
    "game": "Steam Key - Random Stuff Ive Given Away"
  },
  {
    "time": 1717344219000,
    "user": "varlamovs",
    "game": "Steam Key - Random Stuff Ive Given Away"
  },
  {
    "time": 1717345102000,
    "user": "gustavogamarbbr08",
    "game": "Steam Key - Random Stuff Ive Given Away"
  },
  {
    "time": 1717345344000,
    "user": "cepuc_",
    "game": "Sonic Adventure 2"
  },
  {
    "time": 1717345379000,
    "user": "shkolio",
    "game": "Creepy Tale"
  },
  {
    "time": 1717345805000,
    "user": "esfort",
    "game": "Dark Pictures Anthology House of Ashes"
  },
  {
    "time": 1717345854000,
    "user": "daisukemon82",
    "game": "Rage in Peace"
  },
  {
    "time": 1717346276000,
    "user": "alfims",
    "game": "Creaks"
  },
  {
    "time": 1717346476000,
    "user": "pokamae",
    "game": "Narborion Saga"
  },
  {
    "time": 1717346638000,
    "user": "cyborgstyle",
    "game": "Wolflord Werewolf Online"
  },
  {
    "time": 1717346728000,
    "user": "kitty_catty6",
    "game": "Mail Time"
  },
  {
    "time": 1717346736000,
    "user": "cyborgstyle",
    "game": "Corridor Z"
  },
  {
    "time": 1717346986000,
    "user": "aliihsandikmen",
    "game": "Loddlenaut"
  },
  {
    "time": 1717347852000,
    "user": "m1chae185",
    "game": "Steam Key - Random Stuff Ive Given Away"
  },
  {
    "time": 1717348206000,
    "user": "cyborgstyle",
    "game": "Steam Key - Random Stuff Ive Given Away"
  },
  {
    "time": 1717348645000,
    "user": "1garbien1",
    "game": "Amanda The Adventurer"
  },
  {
    "time": 1717348663000,
    "user": "bonus__and_gameover",
    "game": "SCP Secret Files"
  },
  {
    "time": 1717348834000,
    "user": "loskoton",
    "game": "Steam Key - Random Stuff Ive Given Away"
  },
  {
    "time": 1717349170000,
    "user": "xsolarszx",
    "game": "Level Up Simulator"
  },
  {
    "time": 1717349984000,
    "user": "adolfo_kackebart",
    "game": "Slavistan"
  },
  {
    "time": 1717350054000,
    "user": "anyline",
    "game": "Slavistan"
  },
  {
    "time": 1717350483000,
    "user": "kenx00x",
    "game": "Balatro"
  },
  {
    "time": 1717350743000,
    "user": "zoxewi",
    "game": "Steam Key - Random Stuff Ive Given Away"
  },
  {
    "time": 1717351218000,
    "user": "iriyasu_m",
    "game": "XCOM Complete Pack"
  },
  {
    "time": 1717352139000,
    "user": "jonathandkz5",
    "game": "Dishonored Definitive Edition"
  },
  {
    "time": 1717352163000,
    "user": "dynplu",
    "game": "Steam Key - Random Stuff Ive Given Away"
  },
  {
    "time": 1717352412000,
    "user": "tennar7",
    "game": "Rage in Peace"
  },
  {
    "time": 1717352555000,
    "user": "mastersenacu",
    "game": "MirrorMoon EP"
  },
  {
    "time": 1717352771000,
    "user": "davidkli",
    "game": "Guns and Fishes"
  },
  {
    "time": 1717352860000,
    "user": "davidkli",
    "game": "Planet TD"
  },
  {
    "time": 1717353468000,
    "user": "nhnick1",
    "game": "Steam Key - Random Stuff Ive Given Away"
  },
  {
    "time": 1717353516000,
    "user": "hvaki_spark",
    "game": "Cubicle Quest"
  },
  {
    "time": 1717353938000,
    "user": "chi1cag0",
    "game": "Hover Hazard"
  },
  {
    "time": 1717354003000,
    "user": "thanossoul",
    "game": "Rage in Peace"
  },
  {
    "time": 1717354848000,
    "user": "anubiswithcoffee",
    "game": "Rage in Peace"
  },
  {
    "time": 1717354996000,
    "user": "thecyb3rgamer",
    "game": "Slain: Back from Hell"
  },
  {
    "time": 1717355778000,
    "user": "sensitivesuchese",
    "game": "Blaite"
  },
  {
    "time": 1717356380000,
    "user": "noeffnoeff",
    "game": "Fishermurs"
  },
  {
    "time": 1717356446000,
    "user": "anyline",
    "game": "Fishermurs"
  },
  {
    "time": 1717356688000,
    "user": "naipe_maior",
    "game": "Steam Key - Random Stuff Ive Given Away"
  },
  {
    "time": 1717356793000,
    "user": "amoralinzzz",
    "game": "Forgive Me Father 2"
  },
  {
    "time": 1717356832000,
    "user": "housethemous",
    "game": "Keywe"
  },
  {
    "time": 1717357853000,
    "user": "eret1k_game",
    "game": "Steam Key - Random Stuff Ive Given Away"
  },
  {
    "time": 1717357914000,
    "user": "ramzaq",
    "game": "Hell Pie"
  },
  {
    "time": 1717358081000,
    "user": "juan_sebastian028",
    "game": "Remnants of Naezith"
  },
  {
    "time": 1717358132000,
    "user": "v001_",
    "game": "Dream Stone"
  },
  {
    "time": 1717358880000,
    "user": "quenttarantella",
    "game": "Loddlenaut"
  },
  {
    "time": 1717359582000,
    "user": "robert_de_lirio",
    "game": "XCOM Complete Pack"
  },
  {
    "time": 1717359814000,
    "user": "praximo",
    "game": "Exile To Death"
  },
  {
    "time": 1717360488000,
    "user": "ringenburger_",
    "game": "Brother Wings"
  },
  {
    "time": 1717361137000,
    "user": "andreykent1",
    "game": "Beat Stickman Infinity Clones"
  },
  {
    "time": 1717361163000,
    "user": "alburldador",
    "game": "Loddlenaut"
  },
  {
    "time": 1717361714000,
    "user": "yasseruvski",
    "game": "Campfire One of Us Is The Killer"
  },
  {
    "time": 1717362682000,
    "user": "leeogabriel",
    "game": "Steam Key - Random Stuff Ive Given Away"
  },
  {
    "time": 1717363189000,
    "user": "andrade_lucas_",
    "game": "Steam Key - Random Stuff Ive Given Away"
  },
  {
    "time": 1717363968000,
    "user": "kharlyz",
    "game": "Crashmetal Cyberpunk"
  },
  {
    "time": 1717365783000,
    "user": "alexey_lyoga",
    "game": "Steelrising"
  },
  {
    "time": 1717365858000,
    "user": "gabus700",
    "game": "Bravery and Greed"
  },
  {
    "time": 1717366218000,
    "user": "nagibator999lvl",
    "game": "Tin Can"
  },
  {
    "time": 1717366253000,
    "user": "naipe_maior",
    "game": "Titeuf Mega Party"
  },
  {
    "time": 1717366432000,
    "user": "chi1cag0",
    "game": "Space Crew Legendary Edition"
  },
  {
    "time": 1717367272000,
    "user": "logosgames",
    "game": "Yakuza Like A Dragon"
  },
  {
    "time": 1717369326000,
    "user": "ciiniito",
    "game": "Steam Key - Random Stuff Ive Given Away"
  },
  {
    "time": 1717370498000,
    "user": "thatbiscoito",
    "game": "Steam Key - Random Stuff Ive Given Away"
  },
  {
    "time": 1717370633000,
    "user": "thatbiscoito",
    "game": "Magnifico"
  },
  {
    "time": 1717370896000,
    "user": "alcamlu",
    "game": "Steam Key - Random Stuff Ive Given Away"
  },
  {
    "time": 1717371204000,
    "user": "thatbiscoito",
    "game": "Narborion Saga"
  },
  {
    "time": 1717371793000,
    "user": "edusq",
    "game": "Steam Key - Random Stuff Ive Given Away"
  },
  {
    "time": 1717372062000,
    "user": "daniempirerevolution",
    "game": "Overcast Walden and the Werewolf"
  },
  {
    "time": 1717373792000,
    "user": "kazuha_mi_pololo",
    "game": "Coromon"
  },
  {
    "time": 1717373843000,
    "user": "fikkatom",
    "game": "Steam Key - Random Stuff Ive Given Away"
  },
  {
    "time": 1717374736000,
    "user": "pashicus",
    "game": "Steam Key - Random Stuff Ive Given Away"
  },
  {
    "time": 1717374810000,
    "user": "projectofhuman",
    "game": "Steam Key - Random Stuff Ive Given Away"
  },
  {
    "time": 1717375064000,
    "user": "pashicus",
    "game": "Loddlenaut"
  },
  {
    "time": 1717375800000,
    "user": "isunshine_444",
    "game": "Resident Evil Village"
  },
  {
    "time": 1717376696000,
    "user": "murlocxs",
    "game": "Steam Key - Random Stuff Ive Given Away"
  },
  {
    "time": 1717376759000,
    "user": "barneyeldinosaurio132",
    "game": "Steam Key - Random Stuff Ive Given Away"
  },
  {
    "time": 1717376978000,
    "user": "3ak0h",
    "game": "Steam Key - Random Stuff Ive Given Away"
  },
  {
    "time": 1717377009000,
    "user": "chi1cag0",
    "game": "Steam Key - Random Stuff Ive Given Away"
  },
  {
    "time": 1717377286000,
    "user": "lolgems21",
    "game": "Steam Key - Random Stuff Ive Given Away"
  },
  {
    "time": 1717377852000,
    "user": "assistbot00",
    "game": "Steam Key - Random Stuff Ive Given Away"
  },
  {
    "time": 1717378913000,
    "user": "valillao",
    "game": "Steam Key - Random Stuff Ive Given Away"
  },
  {
    "time": 1717378999000,
    "user": "keet2ie",
    "game": "Creaks"
  },
  {
    "time": 1717379053000,
    "user": "keet2ie",
    "game": "Rage in Peace"
  },
  {
    "time": 1717380434000,
    "user": "88caesar8",
    "game": "Rage in Peace"
  },
  {
    "time": 1717383227000,
    "user": "rghype",
    "game": "Steam Key - Random Stuff Ive Given Away"
  },
  {
    "time": 1717383280000,
    "user": "rg_line",
    "game": "Steam Key - Random Stuff Ive Given Away"
  },
  {
    "time": 1717385659000,
    "user": "thunderfulldean",
    "game": "Quake 2"
  },
  {
    "time": 1717386167000,
    "user": "soufant",
    "game": "Steam Key - Random Stuff Ive Given Away"
  },
  {
    "time": 1717388023000,
    "user": "bima1997",
    "game": "Where The Water Tastes Like Wine"
  },
  {
    "time": 1717388665000,
    "user": "t0m0h154",
    "game": "Pixross"
  },
  {
    "time": 1717390366000,
    "user": "0nii01",
    "game": "Steam Key - Random Stuff Ive Given Away"
  },
  {
    "time": 1717391055000,
    "user": "silphat0s",
    "game": "Steam Key - Random Stuff Ive Given Away"
  },
  {
    "time": 1717391182000,
    "user": "w1naz",
    "game": "Amanda The Adventurer"
  },
  {
    "time": 1717393293000,
    "user": "khzvpr",
    "game": "Coromon"
  },
  {
    "time": 1717394021000,
    "user": "chi1cag0",
    "game": "Legend of Keepers Career of a Dungeon Manager"
  },
  {
    "time": 1717395612000,
    "user": "vordired",
    "game": "Steam Key - Random Stuff Ive Given Away"
  },
  {
    "time": 1717396287000,
    "user": "redoneraistlin",
    "game": "Mediterranea Inferno"
  },
  {
    "time": 1717396355000,
    "user": "lokosporgamess",
    "game": "Nascar Heat 5"
  },
  {
    "time": 1717396712000,
    "user": "lokosporgamess",
    "game": "Soulblight"
  },
  {
    "time": 1717397171000,
    "user": "apryed",
    "game": "Dead Island Definitive Edition"
  },
  {
    "time": 1717398026000,
    "user": "flashseal",
    "game": "Loddlenaut"
  },
  {
    "time": 1717398821000,
    "user": "bestfan",
    "game": "Satellite Repairman"
  },
  {
    "time": 1717399594000,
    "user": "eugene_kuz",
    "game": "Chicken Labyrinth Puzzles"
  },
  {
    "time": 1717399627000,
    "user": "eug_alex",
    "game": "Chicken Labyrinth Puzzles"
  },
  {
    "time": 1717400097000,
    "user": "pokamae",
    "game": "Narborion Saga"
  },
  {
    "time": 1717400511000,
    "user": "neliunmih",
    "game": "Starfringe Adversus"
  },
  {
    "time": 1717400700000,
    "user": "agstar",
    "game": "Steam Key - Random Stuff Ive Given Away"
  },
  {
    "time": 1717401340000,
    "user": "pixelsserenity",
    "game": "Steam Key - Random Stuff Ive Given Away"
  },
  {
    "time": 1717401795000,
    "user": "snlthlk",
    "game": "Bartlows Dread Machine"
  },
  {
    "time": 1717402166000,
    "user": "snlthlk",
    "game": "Tell Me Everything"
  },
  {
    "time": 1717402338000,
    "user": "moonlight001122",
    "game": "Honey I Joined a Cult"
  },
  {
    "time": 1717403767000,
    "user": "bananagamingofficial",
    "game": "Steam Key - Random Stuff Ive Given Away"
  },
  {
    "time": 1717404374000,
    "user": "donotworrybhappy",
    "game": "Steam Key - Random Stuff Ive Given Away"
  },
  {
    "time": 1717405171000,
    "user": "sonyfan4pda",
    "game": "System Shock Enhanced Edition"
  },
  {
    "time": 1717405461000,
    "user": "dustdominus",
    "game": "Steam Key - Random Stuff Ive Given Away"
  },
  {
    "time": 1717405704000,
    "user": "onloose",
    "game": "Amanda The Adventurer"
  },
  {
    "time": 1717405872000,
    "user": "lolgems22",
    "game": "Steam Key - Random Stuff Ive Given Away"
  },
  {
    "time": 1717406972000,
    "user": "iluminaria",
    "game": "Paw Paw Paw"
  },
  {
    "time": 1717407716000,
    "user": "ollemeister",
    "game": "Steam Key - Random Stuff Ive Given Away"
  },
  {
    "time": 1717408682000,
    "user": "lipinho03_yt",
    "game": "Steam Key - Random Stuff Ive Given Away"
  },
  {
    "time": 1717408833000,
    "user": "iriyasu_m",
    "game": "Sid Meiers Covert Action"
  },
  {
    "time": 1717408945000,
    "user": "vosterbod_lp",
    "game": "Steam Key - Random Stuff Ive Given Away"
  },
  {
    "time": 1717409273000,
    "user": "andraz201",
    "game": "ATOM RPG Trudograd"
  },
  {
    "time": 1717409316000,
    "user": "vosterbod_lp",
    "game": "Narborion Saga"
  },
  {
    "time": 1717409321000,
    "user": "andraz201",
    "game": "Mars Horizon"
  },
  {
    "time": 1717409493000,
    "user": "andraz201",
    "game": "Loddlenaut"
  },
  {
    "time": 1717409582000,
    "user": "andraz201",
    "game": "Rage in Peace"
  },
  {
    "time": 1717409702000,
    "user": "andraz201",
    "game": "The Big Con"
  },
  {
    "time": 1717410344000,
    "user": "hvaki_spark",
    "game": "Blaite"
  },
  {
    "time": 1717410616000,
    "user": "pharaohako",
    "game": "DARQ Complete Edition"
  },
  {
    "time": 1717411554000,
    "user": "tanoshiiii",
    "game": "INJUSTICE 2 LEGENDARY EDITION"
  },
  {
    "time": 1717411830000,
    "user": "xmarktvx",
    "game": "Magnifico"
  },
  {
    "time": 1717411948000,
    "user": "xmarktvx",
    "game": "Starship Annihilator"
  },
  {
    "time": 1717412082000,
    "user": "tan_426",
    "game": "Wolfenstein The Old Blood"
  },
  {
    "time": 1717412448000,
    "user": "memowho1",
    "game": "Aces and Adventures"
  },
  {
    "time": 1717412458000,
    "user": "tan_426",
    "game": "Deadlink"
  },
  {
    "time": 1717412519000,
    "user": "tan_426",
    "game": "Yakuza 4 Remastered"
  },
  {
    "time": 1717413148000,
    "user": "ajacules",
    "game": "Destroyer The Uboat Hunter"
  },
  {
    "time": 1717413698000,
    "user": "muro_zuark",
    "game": "Gauntlet Slayer Edition"
  },
  {
    "time": 1717413885000,
    "user": "dotienduc96",
    "game": "Guacamelee! Super Turbo Championship Edition"
  },
  {
    "time": 1717414115000,
    "user": "prot3as",
    "game": "Crazy Sapper 3D"
  },
  {
    "time": 1717414192000,
    "user": "charos24",
    "game": "Steam Key - Random Stuff Ive Given Away"
  },
  {
    "time": 1717414269000,
    "user": "prot3as",
    "game": "Soulblight"
  },
  {
    "time": 1717414650000,
    "user": "prot3as",
    "game": "Batman Arkham Knight Premium Edition"
  },
  {
    "time": 1717414971000,
    "user": "prot3as",
    "game": "XCOM Chimera Squad"
  },
  {
    "time": 1717416499000,
    "user": "stardk1",
    "game": "Steam Key - Random Stuff Ive Given Away"
  },
  {
    "time": 1717416624000,
    "user": "richilugn",
    "game": "Steam Key - Random Stuff Ive Given Away"
  },
  {
    "time": 1717417475000,
    "user": "maracasi90",
    "game": "Mortal Kombat 11"
  },
  {
    "time": 1717417481000,
    "user": "phoenix1386",
    "game": "Tales of Vesperia Definitive Edition"
  },
  {
    "time": 1717417751000,
    "user": "zelasis",
    "game": "Merchant of the Skies"
  },
  {
    "time": 1717419975000,
    "user": "justtch",
    "game": "Steam Key - Random Stuff Ive Given Away"
  },
  {
    "time": 1717421051000,
    "user": "tbreeden76",
    "game": "Rage in Peace"
  },
  {
    "time": 1717421338000,
    "user": "purrfectmeowmoew",
    "game": "Exile To Death"
  },
  {
    "time": 1717421958000,
    "user": "vr_ko",
    "game": "Hot Brass"
  },
  {
    "time": 1717421968000,
    "user": "halyava0601",
    "game": "Bravery and Greed"
  },
  {
    "time": 1717421987000,
    "user": "halyava0601",
    "game": "Bravery and Greed"
  },
  {
    "time": 1717422545000,
    "user": "stsemeckii",
    "game": "Treasure Hunter Simulator"
  },
  {
    "time": 1717422826000,
    "user": "murlocxs",
    "game": "Shutshimi"
  },
  {
    "time": 1717423869000,
    "user": "pleiad96",
    "game": "Creaks"
  },
  {
    "time": 1717424340000,
    "user": "forsteamgames",
    "game": "Steam Key - Random Stuff Ive Given Away"
  },
  {
    "time": 1717425003000,
    "user": "lbtstioben",
    "game": "Steam Key - Random Stuff Ive Given Away"
  },
  {
    "time": 1717426348000,
    "user": "kr1sh4n",
    "game": "Steam Key - Random Stuff Ive Given Away"
  },
  {
    "time": 1717426866000,
    "user": "artedeivideogiochi",
    "game": "Steam Key - Random Stuff Ive Given Away"
  },
  {
    "time": 1717428307000,
    "user": "momojo_murs",
    "game": "Fashion Police"
  },
  {
    "time": 1717428451000,
    "user": "justinphan9x",
    "game": "Cult of the Lamb"
  },
  {
    "time": 1717428999000,
    "user": "grosssur",
    "game": "Cheap Golf"
  },
  {
    "time": 1717429035000,
    "user": "grosssur",
    "game": "Eight Mini Racers"
  },
  {
    "time": 1717429059000,
    "user": "grosssur",
    "game": "Ball of Wonder"
  },
  {
    "time": 1717429082000,
    "user": "grosssur",
    "game": "Pill Baby"
  },
  {
    "time": 1717429116000,
    "user": "grosssur",
    "game": "Rover Rescue"
  },
  {
    "time": 1717429594000,
    "user": "kolug90",
    "game": "Steam Key - Random Stuff Ive Given Away"
  },
  {
    "time": 1717429596000,
    "user": "divine_knight1996",
    "game": "Door Kickers Action Squad"
  },
  {
    "time": 1717429859000,
    "user": "constantinrs",
    "game": "Hidden and Dangerous Action Pack"
  },
  {
    "time": 1717430085000,
    "user": "hsunkuei",
    "game": "Steam Key - Random Stuff Ive Given Away"
  },
  {
    "time": 1717430706000,
    "user": "constantinrs",
    "game": "MirrorMoon EP"
  },
  {
    "time": 1717430857000,
    "user": "ikfes01",
    "game": "Steam Key - Random Stuff Ive Given Away"
  },
  {
    "time": 1717431286000,
    "user": "drakonsein",
    "game": "LISA Complete Edition"
  },
  {
    "time": 1717432248000,
    "user": "rina_sav",
    "game": "Cubicle Quest"
  },
  {
    "time": 1717432355000,
    "user": "andrew19001",
    "game": "Fishermurs"
  },
  {
    "time": 1717433122000,
    "user": "vigaristti",
    "game": "Agent in Depth"
  },
  {
    "time": 1717433167000,
    "user": "nyiuxts",
    "game": "Steam Key - Random Stuff Ive Given Away"
  },
  {
    "time": 1717435288000,
    "user": "trulyharmless",
    "game": "Stikir"
  },
  {
    "time": 1717435329000,
    "user": "v001_",
    "game": "Dream Stone"
  },
  {
    "time": 1717435559000,
    "user": "gyq181",
    "game": "Orcs Must Die 2"
  },
  {
    "time": 1717435566000,
    "user": "oegushek",
    "game": "Steam Key - Random Stuff Ive Given Away"
  },
  {
    "time": 1717435979000,
    "user": "lobooscuro3239",
    "game": "Steam Key - Random Stuff Ive Given Away"
  },
  {
    "time": 1717436092000,
    "user": "mincak",
    "game": "Zombie Driver HD"
  },
  {
    "time": 1717436614000,
    "user": "vitaliy_kamalin",
    "game": "Bayonetta"
  },
  {
    "time": 1717437456000,
    "user": "thatbiscoito",
    "game": "Guns and Fishes"
  },
  {
    "time": 1717437645000,
    "user": "eret1k_game",
    "game": "Quake 2"
  },
  {
    "time": 1717442048000,
    "user": "lucifersam29",
    "game": "Rage in Peace"
  },
  {
    "time": 1717442363000,
    "user": "dovak1nn",
    "game": "Rebel Inc Escalation"
  },
  {
    "time": 1717444033000,
    "user": "jonnysonny",
    "game": "Sid Meiers Colonization"
  },
  {
    "time": 1717444959000,
    "user": "qanoma23",
    "game": "Pacific Drive"
  },
  {
    "time": 1717446579000,
    "user": "nikon38",
    "game": "Humankind Definitive Edition"
  },
  {
    "time": 1717447373000,
    "user": "popagaming",
    "game": "Excavation of Hobs Barrow"
  },
  {
    "time": 1717447437000,
    "user": "popagaming",
    "game": "Coromon"
  },
  {
    "time": 1717447531000,
    "user": "popagaming",
    "game": "Love is Dead"
  },
  {
    "time": 1717447690000,
    "user": "popagaming",
    "game": "Shutshimi"
  },
  {
    "time": 1717448031000,
    "user": "kingivingi",
    "game": "Steam Key - Random Stuff Ive Given Away"
  },
  {
    "time": 1717449141000,
    "user": "itzdix69",
    "game": "Road Madness"
  },
  {
    "time": 1717449251000,
    "user": "davidkli",
    "game": "Mind Spheres"
  },
  {
    "time": 1717449710000,
    "user": "idrispukke_",
    "game": "Steam Key - Random Stuff Ive Given Away"
  },
  {
    "time": 1717449776000,
    "user": "piscessculpordwarf",
    "game": "Guilty Gear X2 Reload"
  },
  {
    "time": 1717449969000,
    "user": "georgadze",
    "game": "System Shock Enhanced Edition"
  },
  {
    "time": 1717450181000,
    "user": "asobrabo",
    "game": "Steam Key - Random Stuff Ive Given Away"
  },
  {
    "time": 1717450199000,
    "user": "itzdix69",
    "game": "Steam Key - Random Stuff Ive Given Away"
  },
  {
    "time": 1717451387000,
    "user": "eret1k_game",
    "game": "Steam Key - Random Stuff Ive Given Away"
  },
  {
    "time": 1717451548000,
    "user": "qvqwonderful",
    "game": "Batora Lost Haven"
  },
  {
    "time": 1717451711000,
    "user": "t0m0h154",
    "game": "Pixross"
  },
  {
    "time": 1717451846000,
    "user": "baritonestyx",
    "game": "Dungeon Of Elements"
  },
  {
    "time": 1717451994000,
    "user": "cyborgstyle",
    "game": "Steam Key - Random Stuff Ive Given Away"
  },
  {
    "time": 1717452112000,
    "user": "cyborgstyle",
    "game": "Sid Meier's Ace Patrol Pacific Skies"
  },
  {
    "time": 1717453188000,
    "user": "ingramms",
    "game": "Steam Key - Random Stuff Ive Given Away"
  },
  {
    "time": 1717453400000,
    "user": "tan_426",
    "game": "Mortal Kombat 11"
  },
  {
    "time": 1717453643000,
    "user": "daniempirerevolution",
    "game": "Overcast Walden and the Werewolf"
  },
  {
    "time": 1717454712000,
    "user": "oroku_saki19",
    "game": "Loddlenaut"
  },
  {
    "time": 1717455581000,
    "user": "naipe_maior",
    "game": "Steam Key - Random Stuff Ive Given Away"
  },
  {
    "time": 1717455861000,
    "user": "ferius977",
    "game": "$5 Steam Code"
  },
  {
    "time": 1717455882000,
    "user": "tincelki",
    "game": "$5 Steam Code"
  },
  {
    "time": 1717455898000,
    "user": "gorgoksc",
    "game": "$5 Steam Code"
  },
  {
    "time": 1717455910000,
    "user": "rockcivic",
    "game": "Devil May Cry 4 Special Edition"
  },
  {
    "time": 1717455918000,
    "user": "ciiniito",
    "game": "Steam Key - Random Stuff Ive Given Away"
  },
  {
    "time": 1717455918000,
    "user": "sione89",
    "game": "$5 Steam Code"
  },
  {
    "time": 1717455931000,
    "user": "ooouuut",
    "game": "$5 Steam Code"
  },
  {
    "time": 1717455931000,
    "user": "andy_square",
    "game": "Devil May Cry 4 Special Edition"
  },
  {
    "time": 1717455955000,
    "user": "xthissuxxx",
    "game": "Wayout 2"
  },
  {
    "time": 1717455960000,
    "user": "zittyer",
    "game": "Devil May Cry 4 Special Edition"
  },
  {
    "time": 1717455980000,
    "user": "supercell_777",
    "game": "$5 Steam Code"
  },
  {
    "time": 1717456013000,
    "user": "paymeinwaffles",
    "game": "Wayout 2"
  },
  {
    "time": 1717456041000,
    "user": "wolfdizzzzzzzzzzzzzzzzzz",
    "game": "Neon Space 2"
  },
  {
    "time": 1717456060000,
    "user": "cloud_porcelana",
    "game": "Afterimage"
  },
  {
    "time": 1717456093000,
    "user": "random_machine",
    "game": "$5 Steam Code"
  },
  {
    "time": 1717456228000,
    "user": "ashsenju",
    "game": "Stardew Valley"
  },
  {
    "time": 1717456370000,
    "user": "rna2050",
    "game": "$5 Steam Code"
  },
  {
    "time": 1717456495000,
    "user": "pcompuitguy",
    "game": "$5 Steam Code"
  },
  {
    "time": 1717457176000,
    "user": "wanderfxf",
    "game": "Excavation of Hobs Barrow"
  },
  {
    "time": 1717457439000,
    "user": "alcamlu",
    "game": "Steam Key - Random Stuff Ive Given Away"
  },
  {
    "time": 1717458201000,
    "user": "labent0",
    "game": "$5 Steam Code"
  },
  {
    "time": 1717458221000,
    "user": "miguelh1020",
    "game": "Crazy Sapper 3D"
  },
  {
    "time": 1717458251000,
    "user": "miguelh1020",
    "game": "Exile To Death"
  },
  {
    "time": 1717458270000,
    "user": "rockcivic",
    "game": "Walking Dead Telltale Definitive Edition"
  },
  {
    "time": 1717458544000,
    "user": "tsavop",
    "game": "Neon Space 2"
  },
  {
    "time": 1717458585000,
    "user": "miguelh1020",
    "game": "Creepy Tale"
  },
  {
    "time": 1717458629000,
    "user": "juninho_cps",
    "game": "$5 Steam Code"
  },
  {
    "time": 1717458894000,
    "user": "rockcivic",
    "game": "The Walking Dead New Frontier"
  },
  {
    "time": 1717459087000,
    "user": "arde7777",
    "game": "Symphony of War The Nephilim Saga"
  },
  {
    "time": 1717459098000,
    "user": "rockcivic",
    "game": "The Walking Dead Season 2"
  },
  {
    "time": 1717459562000,
    "user": "alselnk",
    "game": "Coromon"
  },
  {
    "time": 1717460204000,
    "user": "alkeaz",
    "game": "Zombie Driver HD"
  },
  {
    "time": 1717460880000,
    "user": "nudzj",
    "game": "Rage in Peace"
  },
  {
    "time": 1717460911000,
    "user": "nudzj",
    "game": "Rage in Peace"
  },
  {
    "time": 1717461208000,
    "user": "alexiaandreas",
    "game": "$5 Steam Code"
  },
  {
    "time": 1717461213000,
    "user": "naoka_ueno",
    "game": "Devil May Cry 4 Special Edition"
  },
  {
    "time": 1717461834000,
    "user": "edusq",
    "game": "Steam Key - Random Stuff Ive Given Away"
  },
  {
    "time": 1717462461000,
    "user": "spacexdragondog",
    "game": "Devil May Cry 4 Special Edition"
  },
  {
    "time": 1717463271000,
    "user": "murlocxs",
    "game": "Steam Key - Random Stuff Ive Given Away"
  },
  {
    "time": 1717463730000,
    "user": "fikkatom",
    "game": "Steam Key - Random Stuff Ive Given Away"
  },
  {
    "time": 1717463982000,
    "user": "datdud213",
    "game": "$5 Steam Code"
  },
  {
    "time": 1717464214000,
    "user": "nowhaile",
    "game": "Steam Key - Random Stuff Ive Given Away"
  },
  {
    "time": 1717464267000,
    "user": "samuvt2",
    "game": "Steam Key - Random Stuff Ive Given Away"
  },
  {
    "time": 1717464294000,
    "user": "muro_zuark",
    "game": "Chernobyl Commando"
  },
  {
    "time": 1717464295000,
    "user": "qincire",
    "game": "$5 Steam Code"
  },
  {
    "time": 1717464389000,
    "user": "mistvillage",
    "game": "Rage in Peace"
  },
  {
    "time": 1717464391000,
    "user": "muro_zuark",
    "game": "Dream Stone"
  },
  {
    "time": 1717464488000,
    "user": "muro_zuark",
    "game": "Hover Hazard"
  },
  {
    "time": 1717465536000,
    "user": "fancyfancyfancyfancy",
    "game": "Steam Key - Random Stuff Ive Given Away"
  },
  {
    "time": 1717465781000,
    "user": "fancyfancyfancyfancy",
    "game": "Loddlenaut"
  },
  {
    "time": 1717465802000,
    "user": "fancyfancyfancyfancy",
    "game": "Mediterranea Inferno"
  },
  {
    "time": 1717465947000,
    "user": "fancyfancyfancyfancy",
    "game": "Exile To Death"
  },
  {
    "time": 1717465978000,
    "user": "fancyfancyfancyfancy",
    "game": "Exile To Death"
  },
  {
    "time": 1717465996000,
    "user": "fancyfancyfancyfancy",
    "game": "Exile To Death"
  },
  {
    "time": 1717466012000,
    "user": "fancyfancyfancyfancy",
    "game": "Exile To Death"
  },
  {
    "time": 1717466040000,
    "user": "fancyfancyfancyfancy",
    "game": "Exile To Death"
  },
  {
    "time": 1717466190000,
    "user": "meth0dman93",
    "game": "Neon Space 2"
  },
  {
    "time": 1717466469000,
    "user": "smogracing",
    "game": "$5 Steam Code"
  },
  {
    "time": 1717467603000,
    "user": "ura3535",
    "game": "Devil May Cry 4 Special Edition"
  },
  {
    "time": 1717467741000,
    "user": "fancyfancyfancyfancy",
    "game": "Bravery and Greed"
  },
  {
    "time": 1717468350000,
    "user": "byleonid",
    "game": "Neon Space 2"
  },
  {
    "time": 1717468747000,
    "user": "elsim2",
    "game": "Horizon Zero Dawn Complete Edition"
  },
  {
    "time": 1717468970000,
    "user": "byleonid",
    "game": "Loddlenaut"
  },
  {
    "time": 1717469187000,
    "user": "momojo_murs",
    "game": "Foretales"
  },
  {
    "time": 1717469867000,
    "user": "rghype",
    "game": "Steam Key - Random Stuff Ive Given Away"
  },
  {
    "time": 1717469932000,
    "user": "rg_line",
    "game": "Steam Key - Random Stuff Ive Given Away"
  },
  {
    "time": 1717469936000,
    "user": "pragalbhalfc",
    "game": "$5 Steam Code"
  }
]