[
  {
    "time": 1731216306000,
    "user": "oxxra",
    "game": "Steam Key - Random Stuff Ive Given Away"
  },
  {
    "time": 1731216371000,
    "user": "oxxra",
    "game": "Rencounter"
  },
  {
    "time": 1731216675000,
    "user": "oxxra",
    "game": "A Jugglers Tale"
  },
  {
    "time": 1731219974000,
    "user": "arya_nayyar",
    "game": "Steam Key - Random Stuff Ive Given Away"
  },
  {
    "time": 1731221292000,
    "user": "bandokinoji",
    "game": "Excavation of Hobs Barrow"
  },
  {
    "time": 1731221316000,
    "user": "bandokinoji",
    "game": "Steam Key - Random Stuff Ive Given Away"
  },
  {
    "time": 1731221776000,
    "user": "irlandezul",
    "game": "$5 Steam Code"
  },
  {
    "time": 1731221936000,
    "user": "sottovocevideos",
    "game": "There is no Light Enhanced Edition"
  },
  {
    "time": 1731222857000,
    "user": "jmiyeyh4tw19",
    "game": "Steam Key - Random Stuff Ive Given Away"
  },
  {
    "time": 1731224730000,
    "user": "22superviper22",
    "game": "Steam Key - Random Stuff Ive Given Away"
  },
  {
    "time": 1731225249000,
    "user": "k3w3l",
    "game": "Crown Trick"
  },
  {
    "time": 1731225609000,
    "user": "darkarcherua",
    "game": "The Nightmare"
  },
  {
    "time": 1731226206000,
    "user": "tym1988",
    "game": "Stalker Shadow of Chernobyl"
  },
  {
    "time": 1731226275000,
    "user": "mrproucht",
    "game": "Slavistan"
  },
  {
    "time": 1731226612000,
    "user": "frayz271",
    "game": "Steam Key - Random Stuff Ive Given Away"
  },
  {
    "time": 1731227351000,
    "user": "ny_x_x",
    "game": "God of War"
  },
  {
    "time": 1731228278000,
    "user": "zobrymangaa69",
    "game": "Crashmetal Cyberpunk"
  },
  {
    "time": 1731229786000,
    "user": "chaos32777",
    "game": "Danger Scavenger"
  },
  {
    "time": 1731229832000,
    "user": "22superviper22",
    "game": "Retrowave"
  },
  {
    "time": 1731230209000,
    "user": "owersaizz",
    "game": "Steam Key - Random Stuff Ive Given Away"
  },
  {
    "time": 1731230567000,
    "user": "jaryshi",
    "game": "Stranded Alien Dawn"
  }
]